Workbook
Name Raw_Data: 'HR-Employee-Attrition'!$A$1:$AI$1471

Sheet HR-Employee-Attrition
A1: Age | B1: Attrition | C1: BusinessTravel | D1: DailyRate | E1: Department | F1: DistanceFromHome | G1: Education | H1: EducationField | I1: EmployeeCount | J1: EmployeeNumber | K1: EnvironmentSatisfaction | L1: Gender | M1: HourlyRate | N1: JobInvolvement | O1: JobLevel | P1: JobRole | Q1: JobSatisfaction | R1: MaritalStatus | S1: MonthlyIncome | T1: MonthlyRate | U1: NumCompaniesWorked | V1: Over18 | W1: OverTime | X1: PercentSalaryHike | Y1: PerformanceRating | Z1: RelationshipSatisfaction | AA1: StandardHours | AB1: StockOptionLevel | AC1: TotalWorkingYears | AD1: TrainingTimesLastYear | AE1: WorkLifeBalance | AF1: YearsAtCompany | AG1: YearsInCurrentRole | AH1: YearsSinceLastPromotion | AI1: YearsWithCurrManager
A2: 41 | B2: Yes | C2: Travel_Rarely | D2: 1102 | E2: Sales | F2: 1 | G2: 2 | H2: Life Sciences | I2: 1 | J2: 1 | K2: 2 | L2: Female | M2: 94 | N2: 3 | O2: 2 | P2: Sales Executive | Q2: 4 | R2: Single | S2: 5993 | T2: 19479 | U2: 8 | V2: Y | W2: Yes | X2: 11 | Y2: 3 | Z2: 1 | AA2: 80 | AB2: 0 | AC2: 8 | AD2: 0 | AE2: 1 | AF2: 6 | AG2: 4 | AH2: 0 | AI2: 5
A3: 49 | B3: No | C3: Travel_Frequently | D3: 279 | E3: Research & Development | F3: 8 | G3: 1 | H3: Life Sciences | I3: 1 | J3: 2 | K3: 3 | L3: Male | M3: 61 | N3: 2 | O3: 2 | P3: Research Scientist | Q3: 2 | R3: Married | S3: 5130 | T3: 24907 | U3: 1 | V3: Y | W3: No | X3: 23 | Y3: 4 | Z3: 4 | AA3: 80 | AB3: 1 | AC3: 10 | AD3: 3 | AE3: 3 | AF3: 10 | AG3: 7 | AH3: 1 | AI3: 7
A4: 37 | B4: Yes | C4: Travel_Rarely | D4: 1373 | E4: Research & Development | F4: 2 | G4: 2 | H4: Other | I4: 1 | J4: 4 | K4: 4 | L4: Male | M4: 92 | N4: 2 | O4: 1 | P4: Laboratory Technician | Q4: 3 | R4: Single | S4: 2090 | T4: 2396 | U4: 6 | V4: Y | W4: Yes | X4: 15 | Y4: 3 | Z4: 2 | AA4: 80 | AB4: 0 | AC4: 7 | AD4: 3 | AE4: 3 | AF4: 0 | AG4: 0 | AH4: 0 | AI4: 0
A5: 33 | B5: No | C5: Travel_Frequently | D5: 1392 | E5: Research & Development | F5: 3 | G5: 4 | H5: Life Sciences | I5: 1 | J5: 5 | K5: 4 | L5: Female | M5: 56 | N5: 3 | O5: 1 | P5: Research Scientist | Q5: 3 | R5: Married | S5: 2909 | T5: 23159 | U5: 1 | V5: Y | W5: Yes | X5: 11 | Y5: 3 | Z5: 3 | AA5: 80 | AB5: 0 | AC5: 8 | AD5: 3 | AE5: 3 | AF5: 8 | AG5: 7 | AH5: 3 | AI5: 0
A6: 27 | B6: No | C6: Travel_Rarely | D6: 591 | E6: Research & Development | F6: 2 | G6: 1 | H6: Medical | I6: 1 | J6: 7 | K6: 1 | L6: Male | M6: 40 | N6: 3 | O6: 1 | P6: Laboratory Technician | Q6: 2 | R6: Married | S6: 3468 | T6: 16632 | U6: 9 | V6: Y | W6: No | X6: 12 | Y6: 3 | Z6: 4 | AA6: 80 | AB6: 1 | AC6: 6 | AD6: 3 | AE6: 3 | AF6: 2 | AG6: 2 | AH6: 2 | AI6: 2
A7: 32 | B7: No | C7: Travel_Frequently | D7: 1005 | E7: Research & Development | F7: 2 | G7: 2 | H7: Life Sciences | I7: 1 | J7: 8 | K7: 4 | L7: Male | M7: 79 | N7: 3 | O7: 1 | P7: Laboratory Technician | Q7: 4 | R7: Single | S7: 3068 | T7: 11864 | U7: 0 | V7: Y | W7: No | X7: 13 | Y7: 3 | Z7: 3 | AA7: 80 | AB7: 0 | AC7: 8 | AD7: 2 | AE7: 2 | AF7: 7 | AG7: 7 | AH7: 3 | AI7: 6
A8: 59 | B8: No | C8: Travel_Rarely | D8: 1324 | E8: Research & Development | F8: 3 | G8: 3 | H8: Medical | I8: 1 | J8: 10 | K8: 3 | L8: Female | M8: 81 | N8: 4 | O8: 1 | P8: Laboratory Technician | Q8: 1 | R8: Married | S8: 2670 | T8: 9964 | U8: 4 | V8: Y | W8: Yes | X8: 20 | Y8: 4 | Z8: 1 | AA8: 80 | AB8: 3 | AC8: 12 | AD8: 3 | AE8: 2 | AF8: 1 | AG8: 0 | AH8: 0 | AI8: 0
A9: 30 | B9: No | C9: Travel_Rarely | D9: 1358 | E9: Research & Development | F9: 24 | G9: 1 | H9: Life Sciences | I9: 1 | J9: 11 | K9: 4 | L9: Male | M9: 67 | N9: 3 | O9: 1 | P9: Laboratory Technician | Q9: 3 | R9: Divorced | S9: 2693 | T9: 13335 | U9: 1 | V9: Y | W9: No | X9: 22 | Y9: 4 | Z9: 2 | AA9: 80 | AB9: 1 | AC9: 1 | AD9: 2 | AE9: 3 | AF9: 1 | AG9: 0 | AH9: 0 | AI9: 0
A10: 38 | B10: No | C10: Travel_Frequently | D10: 216 | E10: Research & Development | F10: 23 | G10: 3 | H10: Life Sciences | I10: 1 | J10: 12 | K10: 4 | L10: Male | M10: 44 | N10: 2 | O10: 3 | P10: Manufacturing Director | Q10: 3 | R10: Single | S10: 9526 | T10: 8787 | U10: 0 | V10: Y | W10: No | X10: 21 | Y10: 4 | Z10: 2 | AA10: 80 | AB10: 0 | AC10: 10 | AD10: 2 | AE10: 3 | AF10: 9 | AG10: 7 | AH10: 1 | AI10: 8
A11: 36 | B11: No | C11: Travel_Rarely | D11: 1299 | E11: Research & Development | F11: 27 | G11: 3 | H11: Medical | I11: 1 | J11: 13 | K11: 3 | L11: Male | M11: 94 | N11: 3 | O11: 2 | P11: Healthcare Representative | Q11: 3 | R11: Married | S11: 5237 | T11: 16577 | U11: 6 | V11: Y | W11: No | X11: 13 | Y11: 3 | Z11: 2 | AA11: 80 | AB11: 2 | AC11: 17 | AD11: 3 | AE11: 2 | AF11: 7 | AG11: 7 | AH11: 7 | AI11: 7
A12: 35 | B12: No | C12: Travel_Rarely | D12: 809 | E12: Research & Development | F12: 16 | G12: 3 | H12: Medical | I12: 1 | J12: 14 | K12: 1 | L12: Male | M12: 84 | N12: 4 | O12: 1 | P12: Laboratory Technician | Q12: 2 | R12: Married | S12: 2426 | T12: 16479 | U12: 0 | V12: Y | W12: No | X12: 13 | Y12: 3 | Z12: 3 | AA12: 80 | AB12: 1 | AC12: 6 | AD12: 5 | AE12: 3 | AF12: 5 | AG12: 4 | AH12: 0 | AI12: 3
A13: 29 | B13: No | C13: Travel_Rarely | D13: 153 | E13: Research & Development | F13: 15 | G13: 2 | H13: Life Sciences | I13: 1 | J13: 15 | K13: 4 | L13: Female | M13: 49 | N13: 2 | O13: 2 | P13: Laboratory Technician | Q13: 3 | R13: Single | S13: 4193 | T13: 12682 | U13: 0 | V13: Y | W13: Yes | X13: 12 | Y13: 3 | Z13: 4 | AA13: 80 | AB13: 0 | AC13: 10 | AD13: 3 | AE13: 3 | AF13: 9 | AG13: 5 | AH13: 0 | AI13: 8
... A1471: 34 | B1471: No | C1471: Travel_Rarely | D1471: 628 | E1471: Research & Development | F1471: 8 | G1471: 3 | H1471: Medical | I1471: 1 | J1471: 2068 | K1471: 2 | L1471: Male | M1471: 82 | N1471: 4 | O1471: 2 | P1471: Laboratory Technician | Q1471: 3 | R1471: Married | S1471: 4404 | T1471: 10228 | U1471: 2 | V1471: Y | W1471: No | X1471: 12 | Y1471: 3 | Z1471: 1 | AA1471: 80 | AB1471: 0 | AC1471: 6 | AD1471: 3 | AE1471: 4 | AF1471: 4 | AG1471: 3 | AH1471: 1 | AI1471: 2

Sheet Clean Table
A1: EmployeeID | B1: Age | C1: AgeBand | D1: Attrition | E1: Department | F1: Gender | G1: JobLevel | H1: JobRole | I1: MaritalStatus | J1: MonthlyIncome | K1: Tax | L1: Take Home | M1: MonthlyRate | N1: OverTime | O1: PercentSalaryHike | P1: NewSalaryAfter Hike | Q1: AnnualRaiseAmount | R1: SalaryFlag | S1: PerformanceRating | T1: WorkLifeBalance | U1: WorkLifeBalance Level | V1: OverTime2 | W1: YearsAtCompany | X1: EstimatedJoinDate | Y1: NextReviewDate | Z1: Review Flag | AA1: TenureBucket | AB1: Seniority Title Builder | AC1: Full Employee Profile Text Card
A2: =LEFT(H2,2)&"-"&LEFT(E2,3)&"-"&YEAR(TODAY())-W2&"-"&TEXT(ROW()-1,"000") -> Sa-Sal-2020-001 | B2: 41 | C2: =IF(B2<=29,"20-29",IF(B2<=39,"30-39",IF(B2<=49,"40-49","50+"))) -> 40-49 | D2: Yes | E2: Sales | F2: Female | G2: 2 | H2: Sales Executive | I2: Single | J2: 5993 | K2: =IF(J2>13000,J2*30%,IF(J2>7000,J2*22%,IF(J2>3000,J2*15%,J2*7%))) -> 898.95 | L2: =J2-K2 -> 5094.05 | M2: 19479 | N2: Yes | O2: 11 | P2: =J2*(1+(O2/100)) -> 6652.23 | Q2: =(P2-J2)*12 -> 7910.76 | R2: =IF(AND(O2<12,S2=4),"UnderPaid High Performer","Normal") -> Normal | S2: 3 | T2: 1 | U2: {=_xlfn.IFS(T2=1,"Poor",T2=2,"Fair",T2=3,"Good",T2=4,"Excellent")} -> Poor | V2: Yes | W2: 6 | X2: =EDATE(TODAY(),-W2*12) -> 43920 | Y2: =EDATE(X2,(INT(W2/2)+1)*24) -> 46842 | Z2: =IF(Y2<=EDATE(TODAY(),12),"Due Soon","Upcoming") -> Upcoming | AA2: {=_xlfn.IFS(W2>10,"Veteran",W2>=6,"Experienced",W2>=2,"Developing",W2>=0,"New")} -> Experienced | AB2: {=_xlfn.IFS(G2=1,"Junior",G2=2,"Mid-Level",G2=3,"Senior",G2=4,"Lead",G2=5,"Principal")&" "&TRIM(PROPER(H2))} -> Mid-Level Sales Executive | AC2: =A2&" is a "&AB2&" in the "&E2&" department, aged "&B2&", "&LOWER(I2)&" and has been with the Company for "&W2&"years" -> Sa-Sal-2020-001 is a Mid-Level Sales Executive in the Sales department, aged 41, single and has been with the Company for 6years
A3: =LEFT(H3,2)&"-"&LEFT(E3,3)&"-"&YEAR(TODAY())-W3&"-"&TEXT(ROW()-1,"000") -> Re-Res-2016-002 | B3: 49 | C3: =IF(B3<=29,"20-29",IF(B3<=39,"30-39",IF(B3<=49,"40-49","50+"))) -> 40-49 | D3: No | E3: Research & Development | F3: Male | G3: 2 | H3: Research Scientist | I3: Married | J3: 5130 | K3: =IF(J3>13000,J3*30%,IF(J3>7000,J3*22%,IF(J3>3000,J3*15%,J3*7%))) -> 769.5 | L3: =J3-K3 -> 4360.5 | M3: 24907 | N3: No | O3: 23 | P3: =J3*(1+(O3/100)) -> 6309.9 | Q3: =(P3-J3)*12 -> 14158.8 | R3: =IF(AND(O3<12,S3=4),"UnderPaid","Normal") -> Normal | S3: 4 | T3: 3 | U3: {=_xlfn.IFS(T3=1,"Poor",T3=2,"Fair",T3=3,"Good",T3=4,"Excellent")} -> Good | V3: No | W3: 10 | X3: =EDATE(TODAY(),-W3*12) -> 42459 | Y3: =EDATE(X3,(INT(W3/2)+1)*24) -> 46842 | Z3: =IF(Y3<=EDATE(TODAY(),12),"Due Soon","Upcoming") -> Upcoming | AA3: {=_xlfn.IFS(W3>10,"Veteran",W3>=6,"Experienced",W3>=2,"Developing",W3>=0,"New")} -> Experienced | AB3: {=_xlfn.IFS(G3=1,"Junior",G3=2,"Mid-Level",G3=3,"Senior",G3=4,"Lead",G3=5,"Principal")&" "&TRIM(PROPER(H3))} -> Mid-Level Research Scientist | AC3: =A3&" is a "&AB3&" in the "&E3&" department, aged "&B3&", "&LOWER(I3)&" and has been with the Company for "&W3&"years" -> Re-Res-2016-002 is a Mid-Level Research Scientist in the Research & Development department, aged 49, married and has been with the Company for 10years
A4: =LEFT(H4,2)&"-"&LEFT(E4,3)&"-"&YEAR(TODAY())-W4&"-"&TEXT(ROW()-1,"000") -> La-Res-2026-003 | B4: 37 | C4: =IF(B4<=29,"20-29",IF(B4<=39,"30-39",IF(B4<=49,"40-49","50+"))) -> 30-39 | D4: Yes | E4: Research & Development | F4: Male | G4: 1 | H4: Laboratory Technician | I4: Single | J4: 2090 | K4: =IF(J4>13000,J4*30%,IF(J4>7000,J4*22%,IF(J4>3000,J4*15%,J4*7%))) -> 146.3 | L4: =J4-K4 -> 1943.7 | M4: 2396 | N4: Yes | O4: 15 | P4: =J4*(1+(O4/100)) -> 2403.5 | Q4: =(P4-J4)*12 -> 3762 | R4: =IF(AND(O4<12,S4=4),"UnderPaid","Normal") -> Normal | S4: 3 | T4: 3 | U4: {=_xlfn.IFS(T4=1,"Poor",T4=2,"Fair",T4=3,"Good",T4=4,"Excellent")} -> Good | V4: Yes | W4: 0 | X4: =EDATE(TODAY(),-W4*12) -> 46111 | Y4: =EDATE(X4,(INT(W4/2)+1)*24) -> 46842 | Z4: =IF(Y4<=EDATE(TODAY(),12),"Due Soon","Upcoming") -> Upcoming | AA4: {=_xlfn.IFS(W4>10,"Veteran",W4>=6,"Experienced",W4>=2,"Developing",W4>=0,"New")} -> New | AB4: {=_xlfn.IFS(G4=1,"Junior",G4=2,"Mid-Level",G4=3,"Senior",G4=4,"Lead",G4=5,"Principal")&" "&TRIM(PROPER(H4))} -> Junior Laboratory Technician | AC4: =A4&" is a "&AB4&" in the "&E4&" department, aged "&B4&", "&LOWER(I4)&" and has been with the Company for "&W4&"years" -> La-Res-2026-003 is a Junior Laboratory Technician in the Research & Development department, aged 37, single and has been with the Company for 0years
A5: =LEFT(H5,2)&"-"&LEFT(E5,3)&"-"&YEAR(TODAY())-W5&"-"&TEXT(ROW()-1,"000") -> Re-Res-2018-004 | B5: 33 | C5: =IF(B5<=29,"20-29",IF(B5<=39,"30-39",IF(B5<=49,"40-49","50+"))) -> 30-39 | D5: No | E5: Research & Development | F5: Female | G5: 1 | H5: Research Scientist | I5: Married | J5: 2909 | K5: =IF(J5>13000,J5*30%,IF(J5>7000,J5*22%,IF(J5>3000,J5*15%,J5*7%))) -> 203.63 | L5: =J5-K5 -> 2705.37 | M5: 23159 | N5: Yes | O5: 11 | P5: =J5*(1+(O5/100)) -> 3228.99 | Q5: =(P5-J5)*12 -> 3839.88 | R5: =IF(AND(O5<12,S5=4),"UnderPaid","Normal") -> Normal | S5: 3 | T5: 3 | U5: {=_xlfn.IFS(T5=1,"Poor",T5=2,"Fair",T5=3,"Good",T5=4,"Excellent")} -> Good | V5: Yes | W5: 8 | X5: =EDATE(TODAY(),-W5*12) -> 43189 | Y5: =EDATE(X5,(INT(W5/2)+1)*24) -> 46842 | Z5: =IF(Y5<=EDATE(TODAY(),12),"Due Soon","Upcoming") -> Upcoming | AA5: {=_xlfn.IFS(W5>10,"Veteran",W5>=6,"Experienced",W5>=2,"Developing",W5>=0,"New")} -> Experienced | AB5: {=_xlfn.IFS(G5=1,"Junior",G5=2,"Mid-Level",G5=3,"Senior",G5=4,"Lead",G5=5,"Principal")&" "&TRIM(PROPER(H5))} -> Junior Research Scientist | AC5: =A5&" is a "&AB5&" in the "&E5&" department, aged "&B5&", "&LOWER(I5)&" and has been with the Company for "&W5&"years" -> Re-Res-2018-004 is a Junior Research Scientist in the Research & Development department, aged 33, married and has been with the Company for 8years
A6: =LEFT(H6,2)&"-"&LEFT(E6,3)&"-"&YEAR(TODAY())-W6&"-"&TEXT(ROW()-1,"000") -> La-Res-2024-005 | B6: 27 | C6: =IF(B6<=29,"20-29",IF(B6<=39,"30-39",IF(B6<=49,"40-49","50+"))) -> 20-29 | D6: No | E6: Research & Development | F6: Male | G6: 1 | H6: Laboratory Technician | I6: Married | J6: 3468 | K6: =IF(J6>13000,J6*30%,IF(J6>7000,J6*22%,IF(J6>3000,J6*15%,J6*7%))) -> 520.2 | L6: =J6-K6 -> 2947.8 | M6: 16632 | N6: No | O6: 12 | P6: =J6*(1+(O6/100)) -> 3884.16 | Q6: =(P6-J6)*12 -> 4993.92 | R6: =IF(AND(O6<12,S6=4),"UnderPaid","Normal") -> Normal | S6: 3 | T6: 3 | U6: {=_xlfn.IFS(T6=1,"Poor",T6=2,"Fair",T6=3,"Good",T6=4,"Excellent")} -> Good | V6: No | W6: 2 | X6: =EDATE(TODAY(),-W6*12) -> 45381 | Y6: =EDATE(X6,(INT(W6/2)+1)*24) -> 46842 | Z6: =IF(Y6<=EDATE(TODAY(),12),"Due Soon","Upcoming") -> Upcoming | AA6: {=_xlfn.IFS(W6>10,"Veteran",W6>=6,"Experienced",W6>=2,"Developing",W6>=0,"New")} -> Developing | AB6: {=_xlfn.IFS(G6=1,"Junior",G6=2,"Mid-Level",G6=3,"Senior",G6=4,"Lead",G6=5,"Principal")&" "&TRIM(PROPER(H6))} -> Junior Laboratory Technician | AC6: =A6&" is a "&AB6&" in the "&E6&" department, aged "&B6&", "&LOWER(I6)&" and has been with the Company for "&W6&"years" -> La-Res-2024-005 is a Junior Laboratory Technician in the Research & Development department, aged 27, married and has been with the Company for 2years
A7: =LEFT(H7,2)&"-"&LEFT(E7,3)&"-"&YEAR(TODAY())-W7&"-"&TEXT(ROW()-1,"000") -> La-Res-2019-006 | B7: 32 | C7: =IF(B7<=29,"20-29",IF(B7<=39,"30-39",IF(B7<=49,"40-49","50+"))) -> 30-39 | D7: No | E7: Research & Development | F7: Male | G7: 1 | H7: Laboratory Technician | I7: Single | J7: 3068 | K7: =IF(J7>13000,J7*30%,IF(J7>7000,J7*22%,IF(J7>3000,J7*15%,J7*7%))) -> 460.2 | L7: =J7-K7 -> 2607.8 | M7: 11864 | N7: No | O7: 13 | P7: =J7*(1+(O7/100)) -> 3466.84 | Q7: =(P7-J7)*12 -> 4786.08 | R7: =IF(AND(O7<12,S7=4),"UnderPaid","Normal") -> Normal | S7: 3 | T7: 2 | U7: {=_xlfn.IFS(T7=1,"Poor",T7=2,"Fair",T7=3,"Good",T7=4,"Excellent")} -> Fair | V7: No | W7: 7 | X7: =EDATE(TODAY(),-W7*12) -> 43554 | Y7: =EDATE(X7,(INT(W7/2)+1)*24) -> 46476 | Z7: =IF(Y7<=EDATE(TODAY(),12),"Due Soon","Upcoming") -> Due Soon | AA7: {=_xlfn.IFS(W7>10,"Veteran",W7>=6,"Experienced",W7>=2,"Developing",W7>=0,"New")} -> Experienced | AB7: {=_xlfn.IFS(G7=1,"Junior",G7=2,"Mid-Level",G7=3,"Senior",G7=4,"Lead",G7=5,"Principal")&" "&TRIM(PROPER(H7))} -> Junior Laboratory Technician | AC7: =A7&" is a "&AB7&" in the "&E7&" department, aged "&B7&", "&LOWER(I7)&" and has been with the Company for "&W7&"years" -> La-Res-2019-006 is a Junior Laboratory Technician in the Research & Development department, aged 32, single and has been with the Company for 7years
A8: =LEFT(H8,2)&"-"&LEFT(E8,3)&"-"&YEAR(TODAY())-W8&"-"&TEXT(ROW()-1,"000") -> La-Res-2025-007 | B8: 59 | C8: =IF(B8<=29,"20-29",IF(B8<=39,"30-39",IF(B8<=49,"40-49","50+"))) -> 50+ | D8: No | E8: Research & Development | F8: Female | G8: 1 | H8: Laboratory Technician | I8: Married | J8: 2670 | K8: =IF(J8>13000,J8*30%,IF(J8>7000,J8*22%,IF(J8>3000,J8*15%,J8*7%))) -> 186.9 | L8: =J8-K8 -> 2483.1 | M8: 9964 | N8: Yes | O8: 20 | P8: =J8*(1+(O8/100)) -> 3204 | Q8: =(P8-J8)*12 -> 6408 | R8: =IF(AND(O8<12,S8=4),"UnderPaid","Normal") -> Normal | S8: 4 | T8: 2 | U8: {=_xlfn.IFS(T8=1,"Poor",T8=2,"Fair",T8=3,"Good",T8=4,"Excellent")} -> Fair | V8: Yes | W8: 1 | X8: =EDATE(TODAY(),-W8*12) -> 45746 | Y8: =EDATE(X8,(INT(W8/2)+1)*24) -> 46476 | Z8: =IF(Y8<=EDATE(TODAY(),12),"Due Soon","Upcoming") -> Due Soon | AA8: {=_xlfn.IFS(W8>10,"Veteran",W8>=6,"Experienced",W8>=2,"Developing",W8>=0,"New")} -> New | AB8: {=_xlfn.IFS(G8=1,"Junior",G8=2,"Mid-Level",G8=3,"Senior",G8=4,"Lead",G8=5,"Principal")&" "&TRIM(PROPER(H8))} -> Junior Laboratory Technician | AC8: =A8&" is a "&AB8&" in the "&E8&" department, aged "&B8&", "&LOWER(I8)&" and has been with the Company for "&W8&"years" -> La-Res-2025-007 is a Junior Laboratory Technician in the Research & Development department, aged 59, married and has been with the Company for 1years
A9: =LEFT(H9,2)&"-"&LEFT(E9,3)&"-"&YEAR(TODAY())-W9&"-"&TEXT(ROW()-1,"000") -> La-Res-2025-008 | B9: 30 | C9: =IF(B9<=29,"20-29",IF(B9<=39,"30-39",IF(B9<=49,"40-49","50+"))) -> 30-39 | D9: No | E9: Research & Development | F9: Male | G9: 1 | H9: Laboratory Technician | I9: Divorced | J9: 2693 | K9: =IF(J9>13000,J9*30%,IF(J9>7000,J9*22%,IF(J9>3000,J9*15%,J9*7%))) -> 188.51 | L9: =J9-K9 -> 2504.49 | M9: 13335 | N9: No | O9: 22 | P9: =J9*(1+(O9/100)) -> 3285.46 | Q9: =(P9-J9)*12 -> 7109.52 | R9: =IF(AND(O9<12,S9=4),"UnderPaid","Normal") -> Normal | S9: 4 | T9: 3 | U9: {=_xlfn.IFS(T9=1,"Poor",T9=2,"Fair",T9=3,"Good",T9=4,"Excellent")} -> Good | V9: No | W9: 1 | X9: =EDATE(TODAY(),-W9*12) -> 45746 | Y9: =EDATE(X9,(INT(W9/2)+1)*24) -> 46476 | Z9: =IF(Y9<=EDATE(TODAY(),12),"Due Soon","Upcoming") -> Due Soon | AA9: {=_xlfn.IFS(W9>10,"Veteran",W9>=6,"Experienced",W9>=2,"Developing",W9>=0,"New")} -> New | AB9: {=_xlfn.IFS(G9=1,"Junior",G9=2,"Mid-Level",G9=3,"Senior",G9=4,"Lead",G9=5,"Principal")&" "&TRIM(PROPER(H9))} -> Junior Laboratory Technician | AC9: =A9&" is a "&AB9&" in the "&E9&" department, aged "&B9&", "&LOWER(I9)&" and has been with the Company for "&W9&"years" -> La-Res-2025-008 is a Junior Laboratory Technician in the Research & Development department, aged 30, divorced and has been with the Company for 1years
A10: =LEFT(H10,2)&"-"&LEFT(E10,3)&"-"&YEAR(TODAY())-W10&"-"&TEXT(ROW()-1,"000") -> Ma-Res-2017-009 | B10: 38 | C10: =IF(B10<=29,"20-29",IF(B10<=39,"30-39",IF(B10<=49,"40-49","50+"))) -> 30-39 | D10: No | E10: Research & Development | F10: Male | G10: 3 | H10: Manufacturing Director | I10: Single | J10: 9526 | K10: =IF(J10>13000,J10*30%,IF(J10>7000,J10*22%,IF(J10>3000,J10*15%,J10*7%))) -> 2095.72 | L10: =J10-K10 -> 7430.28 | M10: 8787 | N10: No | O10: 21 | P10: =J10*(1+(O10/100)) -> 11526.46 | Q10: =(P10-J10)*12 -> 24005.52 | R10: =IF(AND(O10<12,S10=4),"UnderPaid","Normal") -> Normal | S10: 4 | T10: 3 | U10: {=_xlfn.IFS(T10=1,"Poor",T10=2,"Fair",T10=3,"Good",T10=4,"Excellent")} -> Good | V10: No | W10: 9 | X10: =EDATE(TODAY(),-W10*12) -> 42824 | Y10: =EDATE(X10,(INT(W10/2)+1)*24) -> 46476 | Z10: =IF(Y10<=EDATE(TODAY(),12),"Due Soon","Upcoming") -> Due Soon | AA10: {=_xlfn.IFS(W10>10,"Veteran",W10>=6,"Experienced",W10>=2,"Developing",W10>=0,"New")} -> Experienced | AB10: {=_xlfn.IFS(G10=1,"Junior",G10=2,"Mid-Level",G10=3,"Senior",G10=4,"Lead",G10=5,"Principal")&" "&TRIM(PROPER(H10))} -> Senior Manufacturing Director | AC10: =A10&" is a "&AB10&" in the "&E10&" department, aged "&B10&", "&LOWER(I10)&" and has been with the Company for "&W10&"years" -> Ma-Res-2017-009 is a Senior Manufacturing Director in the Research & Development department, aged 38, single and has been with the Company for 9years
A11: =LEFT(H11,2)&"-"&LEFT(E11,3)&"-"&YEAR(TODAY())-W11&"-"&TEXT(ROW()-1,"000") -> He-Res-2019-010 | B11: 36 | C11: =IF(B11<=29,"20-29",IF(B11<=39,"30-39",IF(B11<=49,"40-49","50+"))) -> 30-39 | D11: No | E11: Research & Development | F11: Male | G11: 2 | H11: Healthcare Representative | I11: Married | J11: 5237 | K11: =IF(J11>13000,J11*30%,IF(J11>7000,J11*22%,IF(J11>3000,J11*15%,J11*7%))) -> 785.55 | L11: =J11-K11 -> 4451.45 | M11: 16577 | N11: No | O11: 13 | P11: =J11*(1+(O11/100)) -> 5917.81 | Q11: =(P11-J11)*12 -> 8169.72 | R11: =IF(AND(O11<12,S11=4),"UnderPaid","Normal") -> Normal | S11: 3 | T11: 2 | U11: {=_xlfn.IFS(T11=1,"Poor",T11=2,"Fair",T11=3,"Good",T11=4,"Excellent")} -> Fair | V11: No | W11: 7 | X11: =EDATE(TODAY(),-W11*12) -> 43554 | Y11: =EDATE(X11,(INT(W11/2)+1)*24) -> 46476 | Z11: =IF(Y11<=EDATE(TODAY(),12),"Due Soon","Upcoming") -> Due Soon | AA11: {=_xlfn.IFS(W11>10,"Veteran",W11>=6,"Experienced",W11>=2,"Developing",W11>=0,"New")} -> Experienced | AB11: {=_xlfn.IFS(G11=1,"Junior",G11=2,"Mid-Level",G11=3,"Senior",G11=4,"Lead",G11=5,"Principal")&" "&TRIM(PROPER(H11))} -> Mid-Level Healthcare Representative | AC11: =A11&" is a "&AB11&" in the "&E11&" department, aged "&B11&", "&LOWER(I11)&" and has been with the Company for "&W11&"years" -> He-Res-2019-010 is a Mid-Level Healthcare Representative in the Research & Development department, aged 36, married and has been with the Company for 7years
A12: =LEFT(H12,2)&"-"&LEFT(E12,3)&"-"&YEAR(TODAY())-W12&"-"&TEXT(ROW()-1,"000") -> La-Res-2021-011 | B12: 35 | C12: =IF(B12<=29,"20-29",IF(B12<=39,"30-39",IF(B12<=49,"40-49","50+"))) -> 30-39 | D12: No | E12: Research & Development | F12: Male | G12: 1 | H12: Laboratory Technician | I12: Married | J12: 2426 | K12: =IF(J12>13000,J12*30%,IF(J12>7000,J12*22%,IF(J12>3000,J12*15%,J12*7%))) -> 169.82 | L12: =J12-K12 -> 2256.18 | M12: 16479 | N12: No | O12: 13 | P12: =J12*(1+(O12/100)) -> 2741.38 | Q12: =(P12-J12)*12 -> 3784.56 | R12: =IF(AND(O12<12,S12=4),"UnderPaid","Normal") -> Normal | S12: 3 | T12: 3 | U12: {=_xlfn.IFS(T12=1,"Poor",T12=2,"Fair",T12=3,"Good",T12=4,"Excellent")} -> Good | V12: No | W12: 5 | X12: =EDATE(TODAY(),-W12*12) -> 44285 | Y12: =EDATE(X12,(INT(W12/2)+1)*24) -> 46476 | Z12: =IF(Y12<=EDATE(TODAY(),12),"Due Soon","Upcoming") -> Due Soon | AA12: {=_xlfn.IFS(W12>10,"Veteran",W12>=6,"Experienced",W12>=2,"Developing",W12>=0,"New")} -> Developing | AB12: {=_xlfn.IFS(G12=1,"Junior",G12=2,"Mid-Level",G12=3,"Senior",G12=4,"Lead",G12=5,"Principal")&" "&TRIM(PROPER(H12))} -> Junior Laboratory Technician | AC12: =A12&" is a "&AB12&" in the "&E12&" department, aged "&B12&", "&LOWER(I12)&" and has been with the Company for "&W12&"years" -> La-Res-2021-011 is a Junior Laboratory Technician in the Research & Development department, aged 35, married and has been with the Company for 5years
A13: =LEFT(H13,2)&"-"&LEFT(E13,3)&"-"&YEAR(TODAY())-W13&"-"&TEXT(ROW()-1,"000") -> La-Res-2017-012 | B13: 29 | C13: =IF(B13<=29,"20-29",IF(B13<=39,"30-39",IF(B13<=49,"40-49","50+"))) -> 20-29 | D13: No | E13: Research & Development | F13: Female | G13: 2 | H13: Laboratory Technician | I13: Single | J13: 4193 | K13: =IF(J13>13000,J13*30%,IF(J13>7000,J13*22%,IF(J13>3000,J13*15%,J13*7%))) -> 628.95 | L13: =J13-K13 -> 3564.05 | M13: 12682 | N13: Yes | O13: 12 | P13: =J13*(1+(O13/100)) -> 4696.16 | Q13: =(P13-J13)*12 -> 6037.92 | R13: =IF(AND(O13<12,S13=4),"UnderPaid","Normal") -> Normal | S13: 3 | T13: 3 | U13: {=_xlfn.IFS(T13=1,"Poor",T13=2,"Fair",T13=3,"Good",T13=4,"Excellent")} -> Good | V13: Yes | W13: 9 | X13: =EDATE(TODAY(),-W13*12) -> 42824 | Y13: =EDATE(X13,(INT(W13/2)+1)*24) -> 46476 | Z13: =IF(Y13<=EDATE(TODAY(),12),"Due Soon","Upcoming") -> Due Soon | AA13: {=_xlfn.IFS(W13>10,"Veteran",W13>=6,"Experienced",W13>=2,"Developing",W13>=0,"New")} -> Experienced | AB13: {=_xlfn.IFS(G13=1,"Junior",G13=2,"Mid-Level",G13=3,"Senior",G13=4,"Lead",G13=5,"Principal")&" "&TRIM(PROPER(H13))} -> Mid-Level Laboratory Technician | AC13: =A13&" is a "&AB13&" in the "&E13&" department, aged "&B13&", "&LOWER(I13)&" and has been with the Company for "&W13&"years" -> La-Res-2017-012 is a Mid-Level Laboratory Technician in the Research & Development department, aged 29, single and has been with the Company for 9years
A14: =LEFT(H14,2)&"-"&LEFT(E14,3)&"-"&YEAR(TODAY())-W14&"-"&TEXT(ROW()-1,"000") -> Re-Res-2021-013 | B14: 31 | C14: =IF(B14<=29,"20-29",IF(B14<=39,"30-39",IF(B14<=49,"40-49","50+"))) -> 30-39 | D14: No | E14: Research & Development | F14: Male | G14: 1 | H14: Research Scientist | I14: Divorced | J14: 2911 | K14: =IF(J14>13000,J14*30%,IF(J14>7000,J14*22%,IF(J14>3000,J14*15%,J14*7%))) -> 203.77 | L14: =J14-K14 -> 2707.23 | M14: 15170 | N14: No | O14: 17 | P14: =J14*(1+(O14/100)) -> 3405.87 | Q14: =(P14-J14)*12 -> 5938.44 | R14: =IF(AND(O14<12,S14=4),"UnderPaid","Normal") -> Normal | S14: 3 | T14: 2 | U14: {=_xlfn.IFS(T14=1,"Poor",T14=2,"Fair",T14=3,"Good",T14=4,"Excellent")} -> Fair | V14: No | W14: 5 | X14: =EDATE(TODAY(),-W14*12) -> 44285 | Y14: =EDATE(X14,(INT(W14/2)+1)*24) -> 46476 | Z14: =IF(Y14<=EDATE(TODAY(),12),"Due Soon","Upcoming") -> Due Soon | AA14: {=_xlfn.IFS(W14>10,"Veteran",W14>=6,"Experienced",W14>=2,"Developing",W14>=0,"New")} -> Developing | AB14: {=_xlfn.IFS(G14=1,"Junior",G14=2,"Mid-Level",G14=3,"Senior",G14=4,"Lead",G14=5,"Principal")&" "&TRIM(PROPER(H14))} -> Junior Research Scientist | AC14: =A14&" is a "&AB14&" in the "&E14&" department, aged "&B14&", "&LOWER(I14)&" and has been with the Company for "&W14&"years" -> Re-Res-2021-013 is a Junior Research Scientist in the Research & Development department, aged 31, divorced and has been with the Company for 5years
... A1471: =LEFT(H1471,2)&"-"&LEFT(E1471,3)&"-"&YEAR(TODAY())-W1471&"-"&TEXT(ROW()-1,"000") -> La-Res-2022-1470 | B1471: 34 | C1471: =IF(B1471<=29,"20-29",IF(B1471<=39,"30-39",IF(B1471<=49,"40-49","50+"))) -> 30-39 | D1471: No | E1471: Research & Development | F1471: Male | G1471: 2 | H1471: Laboratory Technician | I1471: Married | J1471: 4404 | K1471: =IF(J1471>13000,J1471*30%,IF(J1471>7000,J1471*22%,IF(J1471>3000,J1471*15%,J1471*7%))) -> 660.6 | L1471: =J1471-K1471 -> 3743.4 | M1471: 10228 | N1471: No | O1471: 12 | P1471: =J1471*(1+(O1471/100)) -> 4932.48 | Q1471: =(P1471-J1471)*12 -> 6341.76 | R1471: =IF(AND(O1471<12,S1471=4),"UnderPaid","Normal") -> Normal | S1471: 3 | T1471: 4 | U1471: {=_xlfn.IFS(T1471=1,"Poor",T1471=2,"Fair",T1471=3,"Good",T1471=4,"Excellent")} -> Excellent | V1471: No | W1471: 4 | X1471: =EDATE(TODAY(),-W1471*12) -> 44650 | Y1471: =EDATE(X1471,(INT(W1471/2)+1)*24) -> 46842 | Z1471: =IF(Y1471<=EDATE(TODAY(),12),"Due Soon","Upcoming") -> Upcoming | AA1471: {=_xlfn.IFS(W1471>10,"Veteran",W1471>=6,"Experienced",W1471>=2,"Developing",W1471>=0,"New")} -> Developing | AB1471: {=_xlfn.IFS(G1471=1,"Junior",G1471=2,"Mid-Level",G1471=3,"Senior",G1471=4,"Lead",G1471=5,"Principal")&" "&TRIM(PROPER(H1471))} -> Mid-Level Laboratory Technician | AC1471: =A1471&" is a "&AB1471&" in the "&E1471&" department, aged "&B1471&", "&LOWER(I1471)&" and has been with the Company for "&W1471&"years" -> La-Res-2022-1470 is a Mid-Level Laboratory Technician in the Research & Development department, aged 34, married and has been with the Company for 4years

Sheet Clean Summary Table
A1: IBM HR EMPLOYMENT OVERVIEW | D1: UPCOMING REVIEW DATE | G1: Underpaid Employee | I1: WorkLifeBalance | J1: TotalEmployee | K1: OverTime | L1: OverTimeRate
A2: Total Employees | B2: =COUNTA('Clean Table'!A2:A1471) -> 1470 | D2: =COUNTIF('Clean Table'!Z2:Z1471,"Due Soon") -> 796 | G2: =COUNTIF('Clean Table'!R2:R1471,"Underpaid") -> 0 | I2: Poor | J2: =COUNTIF('Clean Table'!$U$2:$U$1471,'Clean Summary Table'!I2) -> 80 | K2: =COUNTIFS('Clean Table'!$U$2:$U$1471,'Clean Summary Table'!I2,'Clean Table'!$V$2:$V$1471,"Yes") -> 22 | L2: =K2/J2 -> 0.275
A3: Departments | B3: =COUNTA(_xlfn.UNIQUE('Clean Table'!E2:E1471)) -> 3 | I3: Fair | J3: =COUNTIF('Clean Table'!$U$2:$U$1471,'Clean Summary Table'!I3) -> 344 | K3: =COUNTIFS('Clean Table'!$U$2:$U$1471,'Clean Summary Table'!I3,'Clean Table'!$V$2:$V$1471,"Yes") -> 104 | L3: =K3/J3 -> 0.30232558
A4: Avg Monthly Income | B4: =AVERAGE('Clean Table'!J2:J1471) -> 6502.9313 | I4: Good | J4: =COUNTIF('Clean Table'!$U$2:$U$1471,'Clean Summary Table'!I4) -> 893 | K4: =COUNTIFS('Clean Table'!$U$2:$U$1471,'Clean Summary Table'!I4,'Clean Table'!$V$2:$V$1471,"Yes") -> 254 | L4: =K4/J4 -> 0.28443449
A5: Avg Take Home Pay | B5: =AVERAGE('Clean Table'!L2:L1471) -> 5148.3446 | I5: Excellent | J5: =COUNTIF('Clean Table'!$U$2:$U$1471,'Clean Summary Table'!I5) -> 153 | K5: =COUNTIFS('Clean Table'!$U$2:$U$1471,'Clean Summary Table'!I5,'Clean Table'!$V$2:$V$1471,"Yes") -> 36 | L5: =K5/J5 -> 0.23529412
A6: Highest Attrition Band | B6: =A23 -> 20-29 | I6: Total Overtime Rate | K6: =SUM(K2:K5)/SUM(J2:J5) -> 0.2829932
A7: Most Stable Band | B7: =A25 -> 40-49
A8: Highest Paid Dept | B8: =A16 -> Research & Development
A9: Lowest Paid Dept | B9: =A15 -> Human Resources
A12: Department salary audit
B13: Gross Salary | F13: Take Home Pay
A14: Department | B14: Average Salary | C14: Minimum Salary | D14: Maximum Salary | E14: Total Salary | F14: Average Take Home | G14: Minimum Take Home | H14: Maximum Take Home | I14: Total Take Home | J14: Tax Burden %
A15: {=_xlfn._xlws.SORT(_xlfn.UNIQUE('Clean Table'!E2:E1471))} -> Human Resources | B15: =AVERAGEIF('Clean Table'!$E$2:$E$1471,'Clean Summary Table'!A15,'Clean Table'!$J$2:$J$1471) -> 6654.5079 | C15: =_xlfn.MINIFS('Clean Table'!$J$2:$J$1471,'Clean Table'!$E$2:$E$1471,'Clean Summary Table'!A15) -> 1555 | D15: =_xlfn.MAXIFS('Clean Table'!$J$2:$J$1471,'Clean Table'!$E$2:$E$1471,'Clean Summary Table'!A15) -> 19717 | E15: =SUMIF('Clean Table'!E2:E1471,'Clean Summary Table'!A15,'Clean Table'!J2:J1471) -> 419234 | F15: =AVERAGEIF('Clean Table'!$E$2:$E$1471,'Clean Summary Table'!A15,'Clean Table'!$L$2:$L$1471) -> 5198.991 | G15: =_xlfn.MINIFS('Clean Table'!$L$2:$L$1471,'Clean Table'!$E$2:$E$1471,'Clean Summary Table'!A15) -> 1446.15 | H15: =_xlfn.MAXIFS('Clean Table'!$L$2:$L$1471,'Clean Table'!$E$2:$E$1471,'Clean Summary Table'!A15) -> 13801.9 | I15: =SUMIF('Clean Table'!$E$2:$E$1471,'Clean Summary Table'!A15,'Clean Table'!$L$2:$L$1471) -> 327536.43 | J15: =(E15-I15)/E15 -> 0.21872646
A16: Research & Development | B16: =AVERAGEIF('Clean Table'!$E$2:$E$1471,'Clean Summary Table'!A16,'Clean Table'!$J$2:$J$1471) -> 6281.2529 | C16: =_xlfn.MINIFS('Clean Table'!$J$2:$J$1471,'Clean Table'!$E$2:$E$1471,'Clean Summary Table'!A16) -> 1009 | D16: =_xlfn.MAXIFS('Clean Table'!$J$2:$J$1471,'Clean Table'!$E$2:$E$1471,'Clean Summary Table'!A16) -> 19999 | E16: =SUMIF('Clean Table'!E3:E1472,'Clean Summary Table'!A16,'Clean Table'!J3:J1472) -> 6036284 | F16: =AVERAGEIF('Clean Table'!$E$2:$E$1471,'Clean Summary Table'!A16,'Clean Table'!$L$2:$L$1471) -> 4968.4437 | G16: =_xlfn.MINIFS('Clean Table'!$L$2:$L$1471,'Clean Table'!$E$2:$E$1471,'Clean Summary Table'!A16) -> 938.37 | H16: =_xlfn.MAXIFS('Clean Table'!$L$2:$L$1471,'Clean Table'!$E$2:$E$1471,'Clean Summary Table'!A16) -> 13999.3 | I16: =SUMIF('Clean Table'!$E$2:$E$1471,'Clean Summary Table'!A16,'Clean Table'!$L$2:$L$1471) -> 4774674.4 | J16: =(E16-I16)/E16 -> 0.20900434
A17: Sales | B17: =AVERAGEIF('Clean Table'!$E$2:$E$1471,'Clean Summary Table'!A17,'Clean Table'!$J$2:$J$1471) -> 6959.1726 | C17: =_xlfn.MINIFS('Clean Table'!$J$2:$J$1471,'Clean Table'!$E$2:$E$1471,'Clean Summary Table'!A17) -> 1052 | D17: =_xlfn.MAXIFS('Clean Table'!$J$2:$J$1471,'Clean Table'!$E$2:$E$1471,'Clean Summary Table'!A17) -> 19847 | E17: =SUMIF('Clean Table'!E4:E1473,'Clean Summary Table'!A17,'Clean Table'!J4:J1473) -> 3097798 | F17: =AVERAGEIF('Clean Table'!$E$2:$E$1471,'Clean Summary Table'!A17,'Clean Table'!$L$2:$L$1471) -> 5528.8244 | G17: =_xlfn.MINIFS('Clean Table'!$L$2:$L$1471,'Clean Table'!$E$2:$E$1471,'Clean Summary Table'!A17) -> 978.36 | H17: =_xlfn.MAXIFS('Clean Table'!$L$2:$L$1471,'Clean Table'!$E$2:$E$1471,'Clean Summary Table'!A17) -> 13892.9 | I17: =SUMIF('Clean Table'!$E$2:$E$1471,'Clean Summary Table'!A17,'Clean Table'!$L$2:$L$1471) -> 2465855.7 | J17: =(E17-I17)/E17 -> 0.20399726
A21: Attrition Risk by Age Band | F21: TENURE BUCKET | G21: Number of Employee | H21: % of WorkForce
A22: Age Band | B22: Total Employee | C22: Left (Yes) | D22: Attrition Rate | F22: New | G22: =COUNTIF(HR[TenureBucket],'Clean Summary Table'!F22) -> 215 | H22: =G22/1470 -> 0.1462585
A23: {=_xlfn._xlws.SORT(_xlfn.UNIQUE('Clean Table'!C2:C1471))} -> 20-29 | B23: =COUNTIF('Clean Table'!$C$2:$C$1471,'Clean Summary Table'!A23) -> 326 | C23: =COUNTIFS('Clean Table'!$C$2:$C$1471,'Clean Summary Table'!A23,'Clean Table'!$D$2:$D$1471,"Yes") -> 91 | D23: =C23/B23 -> 0.2791411 | F23: Developing | G23: =COUNTIF(HR[TenureBucket],'Clean Summary Table'!F23) -> 561 | H23: =G23/1470 -> 0.38163265
A24: 30-39 | B24: =COUNTIF('Clean Table'!$C$2:$C$1471,'Clean Summary Table'!A24) -> 622 | C24: =COUNTIFS('Clean Table'!$C$2:$C$1471,'Clean Summary Table'!A24,'Clean Table'!$D$2:$D$1471,"Yes") -> 89 | D24: =C24/B24 -> 0.14308682 | F24: Experienced | G24: =COUNTIF(HR[TenureBucket],'Clean Summary Table'!F24) -> 448 | H24: =G24/1470 -> 0.3047619
A25: 40-49 | B25: =COUNTIF('Clean Table'!$C$2:$C$1471,'Clean Summary Table'!A25) -> 349 | C25: =COUNTIFS('Clean Table'!$C$2:$C$1471,'Clean Summary Table'!A25,'Clean Table'!$D$2:$D$1471,"Yes") -> 34 | D25: =C25/B25 -> 0.097421203 | F25: Veteran | G25: =COUNTIF(HR[TenureBucket],'Clean Summary Table'!F25) -> 246 | H25: =G25/1470 -> 0.16734694
A26: 50+ | B26: =COUNTIF('Clean Table'!$C$2:$C$1471,'Clean Summary Table'!A26) -> 173 | C26: =COUNTIFS('Clean Table'!$C$2:$C$1471,'Clean Summary Table'!A26,'Clean Table'!$D$2:$D$1471,"Yes") -> 23 | D26: =C26/B26 -> 0.13294798
A28: Total Attrition Rate | B28: =((SUM(C23:C26)/SUM(B23:B26))) -> 0.16122449

Sheet Overview
A1: IBM HR ANALYTICS - DAY 1 & 2 OVERVIEW
A2: 1,470 Employees | 3 Departments
A3: ="Last Updated: "&TEXT(TODAY(),"dd-mmm-yyyy") -> Last Updated: 30-Mar-2026
A9: Department Salary Audit
A10: Department | C10: Average Gross Income | E10: Minimum Gross Income | H10: Maximum Gross Income | J10: Total Gross Income | L10: Total Take Home Income | N10: Tax Burden %
A11: ='Clean Summary Table'!A15 -> Human Resources | C11: ='Clean Summary Table'!B15 -> 6654.5079 | E11: ='Clean Summary Table'!C15 -> 1555 | H11: ='Clean Summary Table'!D15 -> 19717 | J11: ='Clean Summary Table'!E15 -> 419234 | L11: ='Clean Summary Table'!I15 -> 327536.43 | N11: ='Clean Summary Table'!J15 -> 0.21872646
A12: ='Clean Summary Table'!A16 -> Research & Development | C12: ='Clean Summary Table'!B16 -> 6281.2529 | E12: ='Clean Summary Table'!C16 -> 1009 | H12: ='Clean Summary Table'!D16 -> 19999 | J12: ='Clean Summary Table'!E16 -> 6036284 | L12: ='Clean Summary Table'!I16 -> 4774674.4 | N12: ='Clean Summary Table'!J16 -> 0.20900434
A13: ='Clean Summary Table'!A17 -> Sales | C13: ='Clean Summary Table'!B17 -> 6959.1726 | E13: ='Clean Summary Table'!C17 -> 1052 | H13: ='Clean Summary Table'!D17 -> 19847 | J13: ='Clean Summary Table'!E17 -> 3097798 | L13: ='Clean Summary Table'!I17 -> 2465855.7 | N13: ='Clean Summary Table'!J17 -> 0.20399726
A16: Tenure Distribution | H16: Attrition Risk By Age Band
A17: Department | C17: Total Employee | E17: % WorkForce | H17: Age Band | J17: Total | K17: Left | L17: Attrition Rate | N17: Risk Level
A18: ='Clean Summary Table'!F22 -> New | C18: ='Clean Summary Table'!G22 -> 215 | E18: ='Clean Summary Table'!H22 -> 0.1462585 | H18: ='Clean Summary Table'!A23 -> 20-29 | J18: ='Clean Summary Table'!B23 -> 326 | K18: ='Clean Summary Table'!C23 -> 91 | L18: ='Clean Summary Table'!D23 -> 0.2791411 | N18: High
A19: ='Clean Summary Table'!F23 -> Developing | C19: ='Clean Summary Table'!G23 -> 561 | E19: ='Clean Summary Table'!H23 -> 0.38163265 | H19: ='Clean Summary Table'!A24 -> 30-39 | J19: ='Clean Summary Table'!B24 -> 622 | K19: ='Clean Summary Table'!C24 -> 89 | L19: ='Clean Summary Table'!D24 -> 0.14308682 | N19: Medium
A20: ='Clean Summary Table'!F24 -> Experienced | C20: ='Clean Summary Table'!G24 -> 448 | E20: ='Clean Summary Table'!H24 -> 0.3047619 | H20: ='Clean Summary Table'!A25 -> 40-49 | J20: ='Clean Summary Table'!B25 -> 349 | K20: ='Clean Summary Table'!C25 -> 34 | L20: ='Clean Summary Table'!D25 -> 0.097421203 | N20: Low
A21: ='Clean Summary Table'!F25 -> Veteran | C21: ='Clean Summary Table'!G25 -> 246 | E21: ='Clean Summary Table'!H25 -> 0.16734694 | H21: ='Clean Summary Table'!A26 -> 50+ | J21: ='Clean Summary Table'!B26 -> 173 | K21: ='Clean Summary Table'!C26 -> 23 | L21: ='Clean Summary Table'!D26 -> 0.13294798 | N21: Medium
