Workbook
Name Raw_Data: 'HR-Employee-Attrition'!$A$1:$AI$1471

Sheet HR-Employee-Attrition
A1: Age | B1: Attrition | C1: BusinessTravel | D1: DailyRate | E1: Department | F1: DistanceFromHome | G1: Education | H1: EducationField | I1: EmployeeCount | J1: EmployeeNumber | K1: EnvironmentSatisfaction | L1: Gender | M1: HourlyRate | N1: JobInvolvement | O1: JobLevel | P1: JobRole | Q1: JobSatisfaction | R1: MaritalStatus | S1: MonthlyIncome | T1: MonthlyRate | U1: NumCompaniesWorked | V1: Over18 | W1: OverTime | X1: PercentSalaryHike | Y1: PerformanceRating | Z1: RelationshipSatisfaction | AA1: StandardHours | AB1: StockOptionLevel | AC1: TotalWorkingYears | AD1: TrainingTimesLastYear | AE1: WorkLifeBalance | AF1: YearsAtCompany | AG1: YearsInCurrentRole | AH1: YearsSinceLastPromotion | AI1: YearsWithCurrManager
A2: 41 | B2: Yes | C2: Travel_Rarely | D2: 1102 | E2: Sales | F2: 1 | G2: 2 | H2: Life Sciences | I2: 1 | J2: 1 | K2: 2 | L2: Female | M2: 94 | N2: 3 | O2: 2 | P2: Sales Executive | Q2: 4 | R2: Single | S2: 5993 | T2: 19479 | U2: 8 | V2: Y | W2: Yes | X2: 11 | Y2: 3 | Z2: 1 | AA2: 80 | AB2: 0 | AC2: 8 | AD2: 0 | AE2: 1 | AF2: 6 | AG2: 4 | AH2: 0 | AI2: 5
A3: 49 | B3: No | C3: Travel_Frequently | D3: 279 | E3: Research & Development | F3: 8 | G3: 1 | H3: Life Sciences | I3: 1 | J3: 2 | K3: 3 | L3: Male | M3: 61 | N3: 2 | O3: 2 | P3: Research Scientist | Q3: 2 | R3: Married | S3: 5130 | T3: 24907 | U3: 1 | V3: Y | W3: No | X3: 23 | Y3: 4 | Z3: 4 | AA3: 80 | AB3: 1 | AC3: 10 | AD3: 3 | AE3: 3 | AF3: 10 | AG3: 7 | AH3: 1 | AI3: 7
A4: 37 | B4: Yes | C4: Travel_Rarely | D4: 1373 | E4: Research & Development | F4: 2 | G4: 2 | H4: Other | I4: 1 | J4: 4 | K4: 4 | L4: Male | M4: 92 | N4: 2 | O4: 1 | P4: Laboratory Technician | Q4: 3 | R4: Single | S4: 2090 | T4: 2396 | U4: 6 | V4: Y | W4: Yes | X4: 15 | Y4: 3 | Z4: 2 | AA4: 80 | AB4: 0 | AC4: 7 | AD4: 3 | AE4: 3 | AF4: 0 | AG4: 0 | AH4: 0 | AI4: 0
A5: 33 | B5: No | C5: Travel_Frequently | D5: 1392 | E5: Research & Development | F5: 3 | G5: 4 | H5: Life Sciences | I5: 1 | J5: 5 | K5: 4 | L5: Female | M5: 56 | N5: 3 | O5: 1 | P5: Research Scientist | Q5: 3 | R5: Married | S5: 2909 | T5: 23159 | U5: 1 | V5: Y | W5: Yes | X5: 11 | Y5: 3 | Z5: 3 | AA5: 80 | AB5: 0 | AC5: 8 | AD5: 3 | AE5: 3 | AF5: 8 | AG5: 7 | AH5: 3 | AI5: 0
A6: 27 | B6: No | C6: Travel_Rarely | D6: 591 | E6: Research & Development | F6: 2 | G6: 1 | H6: Medical | I6: 1 | J6: 7 | K6: 1 | L6: Male | M6: 40 | N6: 3 | O6: 1 | P6: Laboratory Technician | Q6: 2 | R6: Married | S6: 3468 | T6: 16632 | U6: 9 | V6: Y | W6: No | X6: 12 | Y6: 3 | Z6: 4 | AA6: 80 | AB6: 1 | AC6: 6 | AD6: 3 | AE6: 3 | AF6: 2 | AG6: 2 | AH6: 2 | AI6: 2
A7: 32 | B7: No | C7: Travel_Frequently | D7: 1005 | E7: Research & Development | F7: 2 | G7: 2 | H7: Life Sciences | I7: 1 | J7: 8 | K7: 4 | L7: Male | M7: 79 | N7: 3 | O7: 1 | P7: Laboratory Technician | Q7: 4 | R7: Single | S7: 3068 | T7: 11864 | U7: 0 | V7: Y | W7: No | X7: 13 | Y7: 3 | Z7: 3 | AA7: 80 | AB7: 0 | AC7: 8 | AD7: 2 | AE7: 2 | AF7: 7 | AG7: 7 | AH7: 3 | AI7: 6
A8: 59 | B8: No | C8: Travel_Rarely | D8: 1324 | E8: Research & Development | F8: 3 | G8: 3 | H8: Medical | I8: 1 | J8: 10 | K8: 3 | L8: Female | M8: 81 | N8: 4 | O8: 1 | P8: Laboratory Technician | Q8: 1 | R8: Married | S8: 2670 | T8: 9964 | U8: 4 | V8: Y | W8: Yes | X8: 20 | Y8: 4 | Z8: 1 | AA8: 80 | AB8: 3 | AC8: 12 | AD8: 3 | AE8: 2 | AF8: 1 | AG8: 0 | AH8: 0 | AI8: 0
A9: 30 | B9: No | C9: Travel_Rarely | D9: 1358 | E9: Research & Development | F9: 24 | G9: 1 | H9: Life Sciences | I9: 1 | J9: 11 | K9: 4 | L9: Male | M9: 67 | N9: 3 | O9: 1 | P9: Laboratory Technician | Q9: 3 | R9: Divorced | S9: 2693 | T9: 13335 | U9: 1 | V9: Y | W9: No | X9: 22 | Y9: 4 | Z9: 2 | AA9: 80 | AB9: 1 | AC9: 1 | AD9: 2 | AE9: 3 | AF9: 1 | AG9: 0 | AH9: 0 | AI9: 0
A10: 38 | B10: No | C10: Travel_Frequently | D10: 216 | E10: Research & Development | F10: 23 | G10: 3 | H10: Life Sciences | I10: 1 | J10: 12 | K10: 4 | L10: Male | M10: 44 | N10: 2 | O10: 3 | P10: Manufacturing Director | Q10: 3 | R10: Single | S10: 9526 | T10: 8787 | U10: 0 | V10: Y | W10: No | X10: 21 | Y10: 4 | Z10: 2 | AA10: 80 | AB10: 0 | AC10: 10 | AD10: 2 | AE10: 3 | AF10: 9 | AG10: 7 | AH10: 1 | AI10: 8
A11: 36 | B11: No | C11: Travel_Rarely | D11: 1299 | E11: Research & Development | F11: 27 | G11: 3 | H11: Medical | I11: 1 | J11: 13 | K11: 3 | L11: Male | M11: 94 | N11: 3 | O11: 2 | P11: Healthcare Representative | Q11: 3 | R11: Married | S11: 5237 | T11: 16577 | U11: 6 | V11: Y | W11: No | X11: 13 | Y11: 3 | Z11: 2 | AA11: 80 | AB11: 2 | AC11: 17 | AD11: 3 | AE11: 2 | AF11: 7 | AG11: 7 | AH11: 7 | AI11: 7
A12: 35 | B12: No | C12: Travel_Rarely | D12: 809 | E12: Research & Development | F12: 16 | G12: 3 | H12: Medical | I12: 1 | J12: 14 | K12: 1 | L12: Male | M12: 84 | N12: 4 | O12: 1 | P12: Laboratory Technician | Q12: 2 | R12: Married | S12: 2426 | T12: 16479 | U12: 0 | V12: Y | W12: No | X12: 13 | Y12: 3 | Z12: 3 | AA12: 80 | AB12: 1 | AC12: 6 | AD12: 5 | AE12: 3 | AF12: 5 | AG12: 4 | AH12: 0 | AI12: 3
A13: 29 | B13: No | C13: Travel_Rarely | D13: 153 | E13: Research & Development | F13: 15 | G13: 2 | H13: Life Sciences | I13: 1 | J13: 15 | K13: 4 | L13: Female | M13: 49 | N13: 2 | O13: 2 | P13: Laboratory Technician | Q13: 3 | R13: Single | S13: 4193 | T13: 12682 | U13: 0 | V13: Y | W13: Yes | X13: 12 | Y13: 3 | Z13: 4 | AA13: 80 | AB13: 0 | AC13: 10 | AD13: 3 | AE13: 3 | AF13: 9 | AG13: 5 | AH13: 0 | AI13: 8
... A1471: 34 | B1471: No | C1471: Travel_Rarely | D1471: 628 | E1471: Research & Development | F1471: 8 | G1471: 3 | H1471: Medical | I1471: 1 | J1471: 2068 | K1471: 2 | L1471: Male | M1471: 82 | N1471: 4 | O1471: 2 | P1471: Laboratory Technician | Q1471: 3 | R1471: Married | S1471: 4404 | T1471: 10228 | U1471: 2 | V1471: Y | W1471: No | X1471: 12 | Y1471: 3 | Z1471: 1 | AA1471: 80 | AB1471: 0 | AC1471: 6 | AD1471: 3 | AE1471: 4 | AF1471: 4 | AG1471: 3 | AH1471: 1 | AI1471: 2

Sheet Clean Table
A1: EmployeeID | B1: Age | C1: AgeBand | D1: Attrition | E1: Department | F1: Gender | G1: JobRole | H1: MonthlyIncome | I1: Tax | J1: Take Home | K1: MonthlyRate | L1: YearsAtCompany | M1: TenureBucket
A2: =LEFT(G2,2)&"-"&LEFT(E2,3)&"-"&YEAR(TODAY())-L2&"-"&TEXT(ROW()-1,"000") -> Sa-Sal-2020-001 | B2: 41 | C2: =IF(B2<=29,"20-29",IF(B2<=39,"30-39",IF(B2<=49,"40-49","50+"))) -> 40-49 | D2: Yes | E2: Sales | F2: Female | G2: Sales Executive | H2: 5993 | I2: =IF(H2>13000,H2*30%,IF(H2>7000,H2*22%,IF(H2>3000,H2*15%,H2*7%))) -> 898.95 | J2: =H2-I2 -> 5094.05 | K2: 19479 | L2: 6 | M2: {=_xlfn.IFS(L2>10,"Veteran",L2>=6,"Experienced",L2>=2,"Developing",L2>=0,"New")} -> Experienced
A3: =LEFT(G3,2)&"-"&LEFT(E3,3)&"-"&YEAR(TODAY())-L3&"-"&TEXT(ROW()-1,"000") -> Re-Res-2016-002 | B3: 49 | C3: =IF(B3<=29,"20-29",IF(B3<=39,"30-39",IF(B3<=49,"40-49","50+"))) -> 40-49 | D3: No | E3: Research & Development | F3: Male | G3: Research Scientist | H3: 5130 | I3: =IF(H3>13000,H3*30%,IF(H3>7000,H3*22%,IF(H3>3000,H3*15%,H3*7%))) -> 769.5 | J3: =H3-I3 -> 4360.5 | K3: 24907 | L3: 10 | M3: {=_xlfn.IFS(L3>10,"Veteran",L3>=6,"Experienced",L3>=2,"Developing",L3>=0,"New")} -> Experienced
A4: =LEFT(G4,2)&"-"&LEFT(E4,3)&"-"&YEAR(TODAY())-L4&"-"&TEXT(ROW()-1,"000") -> La-Res-2026-003 | B4: 37 | C4: =IF(B4<=29,"20-29",IF(B4<=39,"30-39",IF(B4<=49,"40-49","50+"))) -> 30-39 | D4: Yes | E4: Research & Development | F4: Male | G4: Laboratory Technician | H4: 2090 | I4: =IF(H4>13000,H4*30%,IF(H4>7000,H4*22%,IF(H4>3000,H4*15%,H4*7%))) -> 146.3 | J4: =H4-I4 -> 1943.7 | K4: 2396 | L4: 0 | M4: {=_xlfn.IFS(L4>10,"Veteran",L4>=6,"Experienced",L4>=2,"Developing",L4>=0,"New")} -> New
A5: =LEFT(G5,2)&"-"&LEFT(E5,3)&"-"&YEAR(TODAY())-L5&"-"&TEXT(ROW()-1,"000") -> Re-Res-2018-004 | B5: 33 | C5: =IF(B5<=29,"20-29",IF(B5<=39,"30-39",IF(B5<=49,"40-49","50+"))) -> 30-39 | D5: No | E5: Research & Development | F5: Female | G5: Research Scientist | H5: 2909 | I5: =IF(H5>13000,H5*30%,IF(H5>7000,H5*22%,IF(H5>3000,H5*15%,H5*7%))) -> 203.63 | J5: =H5-I5 -> 2705.37 | K5: 23159 | L5: 8 | M5: {=_xlfn.IFS(L5>10,"Veteran",L5>=6,"Experienced",L5>=2,"Developing",L5>=0,"New")} -> Experienced
A6: =LEFT(G6,2)&"-"&LEFT(E6,3)&"-"&YEAR(TODAY())-L6&"-"&TEXT(ROW()-1,"000") -> La-Res-2024-005 | B6: 27 | C6: =IF(B6<=29,"20-29",IF(B6<=39,"30-39",IF(B6<=49,"40-49","50+"))) -> 20-29 | D6: No | E6: Research & Development | F6: Male | G6: Laboratory Technician | H6: 3468 | I6: =IF(H6>13000,H6*30%,IF(H6>7000,H6*22%,IF(H6>3000,H6*15%,H6*7%))) -> 520.2 | J6: =H6-I6 -> 2947.8 | K6: 16632 | L6: 2 | M6: {=_xlfn.IFS(L6>10,"Veteran",L6>=6,"Experienced",L6>=2,"Developing",L6>=0,"New")} -> Developing
A7: =LEFT(G7,2)&"-"&LEFT(E7,3)&"-"&YEAR(TODAY())-L7&"-"&TEXT(ROW()-1,"000") -> La-Res-2019-006 | B7: 32 | C7: =IF(B7<=29,"20-29",IF(B7<=39,"30-39",IF(B7<=49,"40-49","50+"))) -> 30-39 | D7: No | E7: Research & Development | F7: Male | G7: Laboratory Technician | H7: 3068 | I7: =IF(H7>13000,H7*30%,IF(H7>7000,H7*22%,IF(H7>3000,H7*15%,H7*7%))) -> 460.2 | J7: =H7-I7 -> 2607.8 | K7: 11864 | L7: 7 | M7: {=_xlfn.IFS(L7>10,"Veteran",L7>=6,"Experienced",L7>=2,"Developing",L7>=0,"New")} -> Experienced
A8: =LEFT(G8,2)&"-"&LEFT(E8,3)&"-"&YEAR(TODAY())-L8&"-"&TEXT(ROW()-1,"000") -> La-Res-2025-007 | B8: 59 | C8: =IF(B8<=29,"20-29",IF(B8<=39,"30-39",IF(B8<=49,"40-49","50+"))) -> 50+ | D8: No | E8: Research & Development | F8: Female | G8: Laboratory Technician | H8: 2670 | I8: =IF(H8>13000,H8*30%,IF(H8>7000,H8*22%,IF(H8>3000,H8*15%,H8*7%))) -> 186.9 | J8: =H8-I8 -> 2483.1 | K8: 9964 | L8: 1 | M8: {=_xlfn.IFS(L8>10,"Veteran",L8>=6,"Experienced",L8>=2,"Developing",L8>=0,"New")} -> New
A9: =LEFT(G9,2)&"-"&LEFT(E9,3)&"-"&YEAR(TODAY())-L9&"-"&TEXT(ROW()-1,"000") -> La-Res-2025-008 | B9: 30 | C9: =IF(B9<=29,"20-29",IF(B9<=39,"30-39",IF(B9<=49,"40-49","50+"))) -> 30-39 | D9: No | E9: Research & Development | F9: Male | G9: Laboratory Technician | H9: 2693 | I9: =IF(H9>13000,H9*30%,IF(H9>7000,H9*22%,IF(H9>3000,H9*15%,H9*7%))) -> 188.51 | J9: =H9-I9 -> 2504.49 | K9: 13335 | L9: 1 | M9: {=_xlfn.IFS(L9>10,"Veteran",L9>=6,"Experienced",L9>=2,"Developing",L9>=0,"New")} -> New
A10: =LEFT(G10,2)&"-"&LEFT(E10,3)&"-"&YEAR(TODAY())-L10&"-"&TEXT(ROW()-1,"000") -> Ma-Res-2017-009 | B10: 38 | C10: =IF(B10<=29,"20-29",IF(B10<=39,"30-39",IF(B10<=49,"40-49","50+"))) -> 30-39 | D10: No | E10: Research & Development | F10: Male | G10: Manufacturing Director | H10: 9526 | I10: =IF(H10>13000,H10*30%,IF(H10>7000,H10*22%,IF(H10>3000,H10*15%,H10*7%))) -> 2095.72 | J10: =H10-I10 -> 7430.28 | K10: 8787 | L10: 9 | M10: {=_xlfn.IFS(L10>10,"Veteran",L10>=6,"Experienced",L10>=2,"Developing",L10>=0,"New")} -> Experienced
A11: =LEFT(G11,2)&"-"&LEFT(E11,3)&"-"&YEAR(TODAY())-L11&"-"&TEXT(ROW()-1,"000") -> He-Res-2019-010 | B11: 36 | C11: =IF(B11<=29,"20-29",IF(B11<=39,"30-39",IF(B11<=49,"40-49","50+"))) -> 30-39 | D11: No | E11: Research & Development | F11: Male | G11: Healthcare Representative | H11: 5237 | I11: =IF(H11>13000,H11*30%,IF(H11>7000,H11*22%,IF(H11>3000,H11*15%,H11*7%))) -> 785.55 | J11: =H11-I11 -> 4451.45 | K11: 16577 | L11: 7 | M11: {=_xlfn.IFS(L11>10,"Veteran",L11>=6,"Experienced",L11>=2,"Developing",L11>=0,"New")} -> Experienced
A12: =LEFT(G12,2)&"-"&LEFT(E12,3)&"-"&YEAR(TODAY())-L12&"-"&TEXT(ROW()-1,"000") -> La-Res-2021-011 | B12: 35 | C12: =IF(B12<=29,"20-29",IF(B12<=39,"30-39",IF(B12<=49,"40-49","50+"))) -> 30-39 | D12: No | E12: Research & Development | F12: Male | G12: Laboratory Technician | H12: 2426 | I12: =IF(H12>13000,H12*30%,IF(H12>7000,H12*22%,IF(H12>3000,H12*15%,H12*7%))) -> 169.82 | J12: =H12-I12 -> 2256.18 | K12: 16479 | L12: 5 | M12: {=_xlfn.IFS(L12>10,"Veteran",L12>=6,"Experienced",L12>=2,"Developing",L12>=0,"New")} -> Developing
A13: =LEFT(G13,2)&"-"&LEFT(E13,3)&"-"&YEAR(TODAY())-L13&"-"&TEXT(ROW()-1,"000") -> La-Res-2017-012 | B13: 29 | C13: =IF(B13<=29,"20-29",IF(B13<=39,"30-39",IF(B13<=49,"40-49","50+"))) -> 20-29 | D13: No | E13: Research & Development | F13: Female | G13: Laboratory Technician | H13: 4193 | I13: =IF(H13>13000,H13*30%,IF(H13>7000,H13*22%,IF(H13>3000,H13*15%,H13*7%))) -> 628.95 | J13: =H13-I13 -> 3564.05 | K13: 12682 | L13: 9 | M13: {=_xlfn.IFS(L13>10,"Veteran",L13>=6,"Experienced",L13>=2,"Developing",L13>=0,"New")} -> Experienced
... A1471: =LEFT(G1471,2)&"-"&LEFT(E1471,3)&"-"&YEAR(TODAY())-L1471&"-"&TEXT(ROW()-1,"000") -> La-Res-2022-1470 | B1471: 34 | C1471: =IF(B1471<=29,"20-29",IF(B1471<=39,"30-39",IF(B1471<=49,"40-49","50+"))) -> 30-39 | D1471: No | E1471: Research & Development | F1471: Male | G1471: Laboratory Technician | H1471: 4404 | I1471: =IF(H1471>13000,H1471*30%,IF(H1471>7000,H1471*22%,IF(H1471>3000,H1471*15%,H1471*7%))) -> 660.6 | J1471: =H1471-I1471 -> 3743.4 | K1471: 10228 | L1471: 4 | M1471: {=_xlfn.IFS(L1471>10,"Veteran",L1471>=6,"Experienced",L1471>=2,"Developing",L1471>=0,"New")} -> Developing

Sheet Clean Summary Table
A1: IBM HR EMPLOYMENT OVERVIEW
A2: Total Employees | B2: =COUNTA('Clean Table'!A2:A1471) -> 1470
A3: Departments | B3: =COUNTA(_xlfn.UNIQUE('Clean Table'!E2:E1471)) -> 3
A4: Avg Monthly Income | B4: =AVERAGE('Clean Table'!H2:H1471) -> 6502.9313
A5: Avg Take Home Pay | B5: =AVERAGE('Clean Table'!J2:J1471) -> 5148.3446
A6: Highest Attrition Band | B6: =A23 -> 20-29
A7: Most Stable Band | B7: =A25 -> 40-49
A8: Highest Paid Dept | B8: =A16 -> Research & Development
A9: Lowest Paid Dept | B9: =A15 -> Human Resources
A12: Department salary audit
B13: Gross Salary | F13: Take Home Pay
A14: Department | B14: Average Salary | C14: Minimum Salary | D14: Maximum Salary | E14: Total Salary | F14: Average Take Home | G14: Minimum Take Home | H14: Maximum Take Home | I14: Total Take Home | J14: Tax Burden %
A15: {=_xlfn._xlws.SORT(_xlfn.UNIQUE('Clean Table'!E2:E1471))} -> Human Resources | B15: =AVERAGEIF('Clean Table'!$E$2:$E$1471,'Clean Summary Table'!A15,'Clean Table'!$H$2:$H$1471) -> 6654.5079 | C15: =_xlfn.MINIFS('Clean Table'!$H$2:$H$1471,'Clean Table'!$E$2:$E$1471,'Clean Summary Table'!A15) -> 1555 | D15: =_xlfn.MAXIFS('Clean Table'!$H$2:$H$1471,'Clean Table'!$E$2:$E$1471,'Clean Summary Table'!A15) -> 19717 | E15: =SUMIF('Clean Table'!E2:E1471,'Clean Summary Table'!A15,'Clean Table'!H2:H1471) -> 419234 | F15: =AVERAGEIF('Clean Table'!$E$2:$E$1471,'Clean Summary Table'!A15,'Clean Table'!$J$2:$J$1471) -> 5198.991 | G15: =_xlfn.MINIFS('Clean Table'!$J$2:$J$1471,'Clean Table'!$E$2:$E$1471,'Clean Summary Table'!A15) -> 1446.15 | H15: =_xlfn.MAXIFS('Clean Table'!$J$2:$J$1471,'Clean Table'!$E$2:$E$1471,'Clean Summary Table'!A15) -> 13801.9 | I15: ` | J15: =(E15-I15)/E15 -> #VALUE!
A16: Research & Development | B16: =AVERAGEIF('Clean Table'!$E$2:$E$1471,'Clean Summary Table'!A16,'Clean Table'!$H$2:$H$1471) -> 6281.2529 | C16: =_xlfn.MINIFS('Clean Table'!$H$2:$H$1471,'Clean Table'!$E$2:$E$1471,'Clean Summary Table'!A16) -> 1009 | D16: =_xlfn.MAXIFS('Clean Table'!$H$2:$H$1471,'Clean Table'!$E$2:$E$1471,'Clean Summary Table'!A16) -> 19999 | E16: =SUMIF('Clean Table'!E3:E1472,'Clean Summary Table'!A16,'Clean Table'!H3:H1472) -> 6036284 | F16: =AVERAGEIF('Clean Table'!$E$2:$E$1471,'Clean Summary Table'!A16,'Clean Table'!$J$2:$J$1471) -> 4968.4437 | G16: =_xlfn.MINIFS('Clean Table'!$J$2:$J$1471,'Clean Table'!$E$2:$E$1471,'Clean Summary Table'!A16) -> 938.37 | H16: =_xlfn.MAXIFS('Clean Table'!$J$2:$J$1471,'Clean Table'!$E$2:$E$1471,'Clean Summary Table'!A16) -> 13999.3 | I16: =SUMIF('Clean Table'!$E$2:$E$1471,'Clean Summary Table'!A16,'Clean Table'!$J$2:$J$1471) -> 4774674.4 | J16: =(E16-I16)/E16 -> 0.20900434
A17: Sales | B17: =AVERAGEIF('Clean Table'!$E$2:$E$1471,'Clean Summary Table'!A17,'Clean Table'!$H$2:$H$1471) -> 6959.1726 | C17: =_xlfn.MINIFS('Clean Table'!$H$2:$H$1471,'Clean Table'!$E$2:$E$1471,'Clean Summary Table'!A17) -> 1052 | D17: =_xlfn.MAXIFS('Clean Table'!$H$2:$H$1471,'Clean Table'!$E$2:$E$1471,'Clean Summary Table'!A17) -> 19847 | E17: =SUMIF('Clean Table'!E4:E1473,'Clean Summary Table'!A17,'Clean Table'!H4:H1473) -> 3097798 | F17: =AVERAGEIF('Clean Table'!$E$2:$E$1471,'Clean Summary Table'!A17,'Clean Table'!$J$2:$J$1471) -> 5528.8244 | G17: =_xlfn.MINIFS('Clean Table'!$J$2:$J$1471,'Clean Table'!$E$2:$E$1471,'Clean Summary Table'!A17) -> 978.36 | H17: =_xlfn.MAXIFS('Clean Table'!$J$2:$J$1471,'Clean Table'!$E$2:$E$1471,'Clean Summary Table'!A17) -> 13892.9 | I17: =SUMIF('Clean Table'!$E$2:$E$1471,'Clean Summary Table'!A17,'Clean Table'!$J$2:$J$1471) -> 2465855.7 | J17: =(E17-I17)/E17 -> 0.20399726
A21: Attrition Risk by Age Band
A22: Age Band | B22: Total Employee | C22: Left (Yes) | D22: Attrition Rate
A23: {=_xlfn._xlws.SORT(_xlfn.UNIQUE('Clean Table'!C2:C1471))} -> 20-29 | B23: =COUNTIF('Clean Table'!$C$2:$C$1471,'Clean Summary Table'!A23) -> 326 | C23: =COUNTIFS('Clean Table'!$C$2:$C$1471,'Clean Summary Table'!A23,'Clean Table'!$D$2:$D$1471,"Yes") -> 91 | D23: =C23/B23 -> 0.2791411
A24: 30-39 | B24: =COUNTIF('Clean Table'!$C$2:$C$1471,'Clean Summary Table'!A24) -> 622 | C24: =COUNTIFS('Clean Table'!$C$2:$C$1471,'Clean Summary Table'!A24,'Clean Table'!$D$2:$D$1471,"Yes") -> 89 | D24: =C24/B24 -> 0.14308682
A25: 40-49 | B25: =COUNTIF('Clean Table'!$C$2:$C$1471,'Clean Summary Table'!A25) -> 349 | C25: =COUNTIFS('Clean Table'!$C$2:$C$1471,'Clean Summary Table'!A25,'Clean Table'!$D$2:$D$1471,"Yes") -> 34 | D25: =C25/B25 -> 0.097421203
A26: 50+ | B26: =COUNTIF('Clean Table'!$C$2:$C$1471,'Clean Summary Table'!A26) -> 173 | C26: =COUNTIFS('Clean Table'!$C$2:$C$1471,'Clean Summary Table'!A26,'Clean Table'!$D$2:$D$1471,"Yes") -> 23 | D26: =C26/B26 -> 0.13294798

Sheet Overview
B10: Attrition Risk by Age Band | G10: Department Average Salary
B11: ='Clean Summary Table'!A22 -> Age Band | C11: Employee | D11: Left | E11: Attrition % | G11: ='Clean Summary Table'!A14 -> Department | H11: ='Clean Summary Table'!B14 -> Average Salary | I11: ='Clean Summary Table'!F14 -> Average Take Home | J11: ='Clean Summary Table'!J14 -> Tax Burden %
B12: ='Clean Summary Table'!A23 -> 20-29 | C12: ='Clean Summary Table'!B23 -> 326 | D12: ='Clean Summary Table'!C23 -> 91 | E12: 0.2791411 | G12: ='Clean Summary Table'!A15 -> Human Resources | H12: ='Clean Summary Table'!B15 -> 6654.5079 | I12: ='Clean Summary Table'!F15 -> 5198.991 | J12: ='Clean Summary Table'!J15 -> #VALUE!
B13: ='Clean Summary Table'!A24 -> 30-39 | C13: ='Clean Summary Table'!B24 -> 622 | D13: ='Clean Summary Table'!C24 -> 89 | E13: 0.14308682 | G13: ='Clean Summary Table'!A16 -> Research & Development | H13: ='Clean Summary Table'!B16 -> 6281.2529 | I13: ='Clean Summary Table'!F16 -> 4968.4437 | J13: ='Clean Summary Table'!J16 -> 0.20900434
B14: ='Clean Summary Table'!A25 -> 40-49 | C14: ='Clean Summary Table'!B25 -> 349 | D14: ='Clean Summary Table'!C25 -> 34 | E14: 0.097421203 | G14: ='Clean Summary Table'!A17 -> Sales | H14: ='Clean Summary Table'!B17 -> 6959.1726 | I14: ='Clean Summary Table'!F17 -> 5528.8244 | J14: ='Clean Summary Table'!J17 -> 0.20399726
B15: ='Clean Summary Table'!A26 -> 50+ | C15: ='Clean Summary Table'!B26 -> 173 | D15: ='Clean Summary Table'!C26 -> 23 | E15: 0.13294798
G16: Department Salary Analysis
G17: ='Clean Summary Table'!A14 -> Department | H17: ='Clean Summary Table'!E14 -> Total Salary | I17: ='Clean Summary Table'!I14 -> Total Take Home | J17: Difference
B18: Salary Range Audit | G18: ='Clean Summary Table'!A15 -> Human Resources | H18: ='Clean Summary Table'!E15 -> 419234 | I18: ='Clean Summary Table'!I15 -> ` | J18: =H18-I18 -> #VALUE!
B19: ='Clean Summary Table'!A14 -> Department | C19: Min Salary | D19: Max Salary | E19: Spread | G19: ='Clean Summary Table'!A16 -> Research & Development | H19: ='Clean Summary Table'!E16 -> 6036284 | I19: ='Clean Summary Table'!I16 -> 4774674.4 | J19: =H19-I19 -> 1261609.6
B20: ='Clean Summary Table'!A15 -> Human Resources | C20: ='Clean Summary Table'!C15 -> 1555 | D20: ='Clean Summary Table'!D15 -> 19717 | E20: =D20-C20 -> 18162 | G20: ='Clean Summary Table'!A17 -> Sales | H20: ='Clean Summary Table'!E17 -> 3097798 | I20: ='Clean Summary Table'!I17 -> 2465855.7 | J20: =H20-I20 -> 631942.31
B21: ='Clean Summary Table'!A16 -> Research & Development | C21: ='Clean Summary Table'!C16 -> 1009 | D21: ='Clean Summary Table'!D16 -> 19999 | E21: =D21-C21 -> 18990
B22: ='Clean Summary Table'!A17 -> Sales | C22: ='Clean Summary Table'!C17 -> 1052 | D22: ='Clean Summary Table'!D17 -> 19847 | E22: =D22-C22 -> 18795
